{
	"required": true,
	"minVersion": "0.8",
	"package": "ru.betterend.mixin.common",
	"compatibilityLevel": "JAVA_16",
	"mixins": [
		"ChorusPlantFeatureMixin",
		"PlayerAdvancementsMixin",
		"ChorusFlowerBlockMixin",
		"StructureFeaturesMixin",
		"NoiseInterpolatorMixin",
		"ChorusPlantBlockMixin",
		"EndPodiumFeatureMixin",
		"EndDragonFightMixin",
		"WorldGenRegionMixin",
		"BlockBehaviourMixin",
		"NoiseChunkAccessor",
		"DimensionTypeMixin",
		"CraftingMenuMixin",
		"LivingEntityMixin",
		"ServerPlayerMixin",
		"SpikeFeatureMixin",
		"ServerLevelMixin",
		"NoiseChunkMixin",
		"EnderManMixin",
		"EndSpikeMixin",
		"MonsterMixin",
		"EntityMixin",
		"PlayerMixin",
		"SlimeMixin",
		"SpawnRestrictionAccessor",
		"**BCLIB**",
		"bclib.BiomeGenerationSettingsAccessor",
		"bclib.shears.DiggingEnchantmentMixin",
		"bclib.shears.ItemPredicateBuilderMixin",
		"bclib.LayerLightSectionStorageMixin",
		"bclib.NoiseBasedChunkGeneratorMixin",
		"bclib.NoiseGeneratorSettingsMixin",
		"bclib.SurfaceRulesContextAccessor",
		"bclib.EnchantingTableBlockMixin",
		"bclib.shears.TripWireBlockMixin",
		"bclib.StructureFeaturesAccessor",
		"bclib.MobSpawnSettingsAccessor",
		"bclib.StructureFeatureAccessor",
		"bclib.shears.BeehiveBlockMixin",
		"bclib.shears.PumpkinBlockMixin",
		"bclib.shears.MushroomCowMixin",
		"bclib.ComposterBlockAccessor",
		"bclib.PotionBrewingAccessor",
		"bclib.RecipeManagerAccessor",
		"bclib.shears.SnowGolemMixin",
		"bclib.MinecraftServerMixin",
		"bclib.NetherBiomeDataMixin",
		"bclib.PistonBaseBlockMixin",
		"bclib.TheEndBiomeDataMixin",
		"bclib.BlockBehaviourMixin",
		"bclib.BlockStateBaseMixin",
		"bclib.ChunkGeneratorMixin",
		"bclib.MappedRegistryMixin",
		"bclib.WorldGenRegionMixin",
		"bclib.DiggerItemAccessor",
		"bclib.DimensionTypeMixin",
		"bclib.RecipeManagerMixin",
		"bclib.RecipeManagerMixin",
		"bclib.ShovelItemAccessor",
		"bclib.BoneMealItemMixin",
		"bclib.CraftingMenuMixin",
		"bclib.shears.SheepMixin",
		"bclib.PortalShapeMixin",
		"bclib.ServerLevelMixin",
		"bclib.BiomeSourceMixin",
		"bclib.AnvilBlockMixin",
		"bclib.AnvilMenuMixin",
		"bclib.ItemStackMixin",
		"bclib.TagLoaderMixin",
		"bclib.BiomeAccessor",
		"bclib.MainMixin",
		"** FABRIC **",
		"fabric.AbstractBlockSettingsAccessor",
		"fabric.AbstractBlockAccessor"
	],
	"injectors": {
		"defaultRequire": 1
	}
}